LICENSE
MANIFEST.in
README.md
setup.cfg
setup.py
versioneer.py
./.gitattributes
./CODE_OF_CONDUCT.md
./CONTRIBUTING.md
./LICENSE
./MANIFEST.in
./README.md
./setup.cfg
./setup.py
./versioneer.py
./htmlmerger/__init__.py
./htmlmerger/_version.py
./htmlmerger/htmlmerger.py
./htmlmerger.egg-info/PKG-INFO
./htmlmerger.egg-info/SOURCES.txt
./htmlmerger.egg-info/dependency_links.txt
./htmlmerger.egg-info/top_level.txt
./tests/__init__.py
./tests/conftest.py
./tests/test_htmlmerger.py
./tests/data/expected.html
./tests/data/input/f1.html
./tests/data/input/f2.html
htmlmerger/__init__.py
htmlmerger/_version.py
htmlmerger/htmlmerger.py
htmlmerger.egg-info/PKG-INFO
htmlmerger.egg-info/SOURCES.txt
htmlmerger.egg-info/dependency_links.txt
htmlmerger.egg-info/top_level.txt
tests/__init__.py
tests/conftest.py
tests/test_htmlmerger.py